struct_model/__init__.py
struct_model/model.py
struct_model/types.py
struct_model_python-0.2.0.dist-info/LICENSE
struct_model_python-0.2.0.dist-info/METADATA
struct_model_python-0.2.0.dist-info/WHEEL
struct_model_python-0.2.0.dist-info/RECORD
